setup.py
twecoll3.py
twecoll3.egg-info/PKG-INFO
twecoll3.egg-info/SOURCES.txt
twecoll3.egg-info/dependency_links.txt
twecoll3.egg-info/entry_points.txt
twecoll3.egg-info/requires.txt
twecoll3.egg-info/top_level.txt