Metadata-Version: 1.0
Name: twecoll3
Version: 2.0.0
Summary: CLI tool to create gdf and gexf files of social networks for use with Gephi
Home-page: https://github.com/lucahammer/twecoll3
Author: Luca Hammer
Author-email: UNKNOWN
License: UNKNOWN
Platform: UNKNOWN
